yapcache/__about__.py
yapcache/__init__.py
yapcache/cache_item.py
yapcache/compat.py
yapcache/distlock.py
yapcache/caches/__init__.py
yapcache/caches/memory.py
yapcache/caches/null.py
yapcache/caches/redis.py
yapcache/serializers/__init__.py
yapcache/serializers/pickle.py
yapcache-0.1.23.dist-info/METADATA
yapcache-0.1.23.dist-info/WHEEL
yapcache-0.1.23.dist-info/licenses/LICENSE.txt
yapcache-0.1.23.dist-info/RECORD
