Metadata-Version: 2.4
Name: yapcache
Version: 0.1.23
Project-URL: Documentation, https://github.com/ecarrara/yapcache#readme
Project-URL: Issues, https://github.com/ecarrara/yapcache/issues
Project-URL: Source, https://github.com/ecarrara/yapcache
Author-email: Erle Carrara <carrara.erle@gmail.com>
License-Expression: MIT
License-File: LICENSE.txt
Classifier: Framework :: AsyncIO
Classifier: Programming Language :: Python
Classifier: Programming Language :: Python :: 3.10
Classifier: Programming Language :: Python :: 3.11
Classifier: Programming Language :: Python :: 3.12
Classifier: Programming Language :: Python :: Implementation :: CPython
Classifier: Programming Language :: Python :: Implementation :: PyPy
Requires-Python: >=3.8
Requires-Dist: cachebox<6,>=5
Requires-Dist: redis<6,>=5.0
Requires-Dist: typing-extensions>=4.4
